openflexure_microscope_client/__init__.py
openflexure_microscope_client/microscope_client.py
openflexure_microscope_client-0.1.8.dist-info/METADATA
openflexure_microscope_client-0.1.8.dist-info/WHEEL
openflexure_microscope_client-0.1.8.dist-info/RECORD
