Metadata-Version: 2.1
Name: openflexure-microscope-client
Version: 0.1.8
Summary: Python client code for the OpenFlexure Microscope
Home-page: https://gitlab.com/openflexure/openflexure-microscope-pyclient/
License: LGPL-3.0-or-later
Author: Richard Bowman
Author-email: richard.bowman@cantab.net
Requires-Python: >=3.7,<4.0
Classifier: License :: OSI Approved :: GNU Lesser General Public License v3 or later (LGPLv3+)
Classifier: Programming Language :: Python :: 3
Classifier: Programming Language :: Python :: 3.7
Classifier: Programming Language :: Python :: 3.8
Classifier: Programming Language :: Python :: 3.9
Classifier: Programming Language :: Python :: 3.10
Classifier: Programming Language :: Python :: 3.11
Requires-Dist: Pillow (>=9.0,<10.0)
Requires-Dist: numpy (>=1.21,<2.0)
Requires-Dist: requests (>=2.28,<3.0)
Requires-Dist: zeroconf (>=0.39,<0.40)
